envhealth/__init__.py
envhealth/__main__.py
envhealth/checker.py
envhealth/cli.py
envhealth/cuda_benchmark.py
envhealth/network_check.py
envhealth/pdf_report.py
envhealth/reporter.py
envhealth/security_check.py
envhealth/version_drift.py
envhealth-1.0.0.dist-info/licenses/LICENSE
envhealth-1.0.0.dist-info/METADATA
envhealth-1.0.0.dist-info/WHEEL
envhealth-1.0.0.dist-info/entry_points.txt
envhealth-1.0.0.dist-info/top_level.txt
envhealth-1.0.0.dist-info/RECORD
