Metadata-Version: 2.4
Name: envhealth
Version: 1.0.0
Summary: Environment health checker that validates Python runtime, OS, dependencies, variables and system readiness
Author-email: Rohan <rohanroni2019@gmail.com>
License: MIT
Project-URL: Homepage, https://github.com/Rohan7654/envhealth
Project-URL: Issues, https://github.com/Rohan7654/envhealth/issues
Keywords: environment,system health,diagnostics,python tooling,debugging
Classifier: Programming Language :: Python :: 3
Classifier: Programming Language :: Python :: 3 :: Only
Classifier: Programming Language :: Python :: 3.8
Classifier: Programming Language :: Python :: 3.9
Classifier: Programming Language :: Python :: 3.10
Classifier: Programming Language :: Python :: 3.11
Classifier: License :: OSI Approved :: MIT License
Classifier: Operating System :: OS Independent
Classifier: Environment :: Console
Classifier: Intended Audience :: Developers
Classifier: Topic :: System :: Monitoring
Requires-Python: >=3.8
License-File: LICENSE
Requires-Dist: psutil
Requires-Dist: requests
Requires-Dist: reportlab
Dynamic: license-file
